{
	"abstract" : true,
	"artifacts" : 
	[
		{
			"path" : "/home/nl455/miniconda3/envs/ros_env/lib/libQt5Gui.so.5.15.15"
		}
	],
	"backtrace" : 5,
	"backtraceGraph" : 
	{
		"commands" : 
		[
			"add_library",
			"find_package",
			"set_property",
			"_populate_Gui_target_properties"
		],
		"files" : 
		[
			"/home/nl455/miniconda3/envs/ros_env/lib/cmake/Qt5Gui/Qt5GuiConfig.cmake",
			"/home/nl455/miniconda3/envs/ros_env/lib/cmake/Qt5Widgets/Qt5WidgetsConfig.cmake",
			"CMakeLists.txt"
		],
		"nodes" : 
		[
			{
				"file" : 2
			},
			{
				"command" : 1,
				"file" : 2,
				"line" : 30,
				"parent" : 0
			},
			{
				"file" : 1,
				"parent" : 1
			},
			{
				"command" : 1,
				"file" : 1,
				"line" : 100,
				"parent" : 2
			},
			{
				"file" : 0,
				"parent" : 3
			},
			{
				"command" : 0,
				"file" : 0,
				"line" : 144,
				"parent" : 4
			},
			{
				"command" : 3,
				"file" : 0,
				"line" : 202,
				"parent" : 4
			},
			{
				"command" : 2,
				"file" : 0,
				"line" : 45,
				"parent" : 6
			}
		]
	},
	"codemodelVersion" : 
	{
		"major" : 2,
		"minor" : 9
	},
	"id" : "Qt5::Gui::@6890427a1f51a3e7e1df",
	"imported" : true,
	"interfaceCompileDependencies" : 
	[
		{
			"backtrace" : 7,
			"id" : "Qt5::Core::@6890427a1f51a3e7e1df"
		}
	],
	"interfaceLinkLibraries" : 
	[
		{
			"backtrace" : 7,
			"id" : "Qt5::Core::@6890427a1f51a3e7e1df"
		}
	],
	"local" : true,
	"name" : "Qt5::Gui",
	"nameOnDisk" : "libQt5Gui.so.5.15.15",
	"paths" : 
	{
		"build" : ".",
		"source" : "."
	},
	"sources" : [],
	"type" : "SHARED_LIBRARY"
}
